kb/__init__.py
kb/views.py
kb/feeds.py
kb/admin.py
kb/forms.py
kb/models.py
kb/middleware.py
kb/search_indexes.py
kb/settings.py
kb/urls.py
kb/migrations/__init__.py
kb/migrations/0001_initial.py
kb/article/__init__.py
kb/article/views.py
kb/article/admin.py
kb/article/forms.py
kb/article/querysets.py
kb/article/models.py
kb/article/search_indexes.py
kb/article/managers.py
kb/article/urls.py
kb/templatetags/__init__.py
kb/templatetags/kbtags.py
kb/vote/__init__.py
kb/vote/utils.py
kb/vote/views.py
kb/vote/admin.py
kb/vote/models.py
kb/vote/urls.py
kb/templates/kb/inclusion_tags/feedback.html
kb/templates/kb/inclusion_tags/feedback_extender.html
kb/templates/search/indexes/kb/article_text.txt
kb/category/__init__.py
kb/category/views.py
kb/category/feeds.py
kb/category/admin.py
kb/category/forms.py
kb/category/querysets.py
kb/category/models.py
kb/category/managers.py
kb/category/urls.py
kb/base/__init__.py
kb/base/views.py
kb/base/behaviours.py
kb/base/querysets.py
kb/base/choices.py
kb/base/search_indexes.py
kb/static/kb/js/feedback.js
django_kb-0.2.0.dist-info/RECORD
django_kb-0.2.0.dist-info/WHEEL
django_kb-0.2.0.dist-info/DESCRIPTION.rst
django_kb-0.2.0.dist-info/top_level.txt
django_kb-0.2.0.dist-info/METADATA
django_kb-0.2.0.dist-info/metadata.json
