Metadata-Version: 2.0
Name: django-kb
Version: 0.2.0
Summary: Simple knowledge base made with django
Home-page: https://github.com/eliostvs/django-kb
Author: Elio Esteves Duarte
Author-email: elio.esteves.duarte@gmail.com
License: BSD
Keywords: django,knowledge base
Platform: UNKNOWN
Classifier: Development Status :: 4 - Beta
Classifier: Framework :: Django
Classifier: Intended Audience :: Developers
Classifier: License :: OSI Approved :: BSD License
Classifier: Natural Language :: English
Classifier: Programming Language :: Python :: 2
Classifier: Programming Language :: Python :: 2.6
Classifier: Programming Language :: Python :: 2.7
Classifier: Programming Language :: Python :: 3
Classifier: Programming Language :: Python :: 3.3
Classifier: Programming Language :: Python :: 3.4
Requires-Dist: Django (>=1.6,<1.7)
Requires-Dist: South (>=0.8.4,<1.0)
Requires-Dist: django-braces (>=1.4.0)
Requires-Dist: django-choices (>=1.3.0)
Requires-Dist: django-haystack (>=2.2.0)
Requires-Dist: django-model-utils (>=2.2.0)
Requires-Dist: django-taggit (>=0.12.1)
Requires-Dist: django-markupfield (==1.2.1)
Requires-Dist: pytz (>=2014.4)
